nexira_ai_package/__init__.py
nexira_ai_package/app_config.py
nexira_ai_package/db_handler.py
nexira_ai_package/initialise_webhook.py
nexira_ai_package/main.py
nexira_ai_package/telegram_bot.py
nexira_ai_package/chat_history/__init__.py
nexira_ai_package/chat_history/memory_handler.py
nexira_ai_package/chat_history/routes.py
nexira_ai_package/chat_history/schema.py
nexira_ai_package/synthesis_data/__init__.py
nexira_ai_package/synthesis_data/synthetic_data.py
nexira_ai_package/vector_db/__init__.py
nexira_ai_package/vector_db/agent_manager.py
nexira_ai_package/vector_db/data_parser.py
nexira_ai_package/vector_db/image_processor.py
nexira_ai_package/vector_db/main_agent.py
nexira_ai_package/vector_db/memory_handler.py
nexira_ai_package/vector_db/routes.py
nexira_ai_package/vector_db/nexira_docs/BLOCK_CLANS_WEAPONS.pdf
nexira_ai_package/vector_db/nexira_docs/MINI_MAVIA.pdf
nexira_ai_package-0.1.6.dist-info/METADATA
nexira_ai_package-0.1.6.dist-info/WHEEL
nexira_ai_package-0.1.6.dist-info/top_level.txt
nexira_ai_package-0.1.6.dist-info/RECORD
