Metadata-Version: 2.4
Name: nexira-ai-package
Version: 0.1.6
Summary: Add your description here
Requires-Python: >=3.13
Requires-Dist: argilla>=2.8.0
Requires-Dist: bs4>=0.0.2
Requires-Dist: einops>=0.8.1
Requires-Dist: fastapi>=0.115.12
Requires-Dist: flashrank>=0.2.10
Requires-Dist: langchain>=0.3.25
Requires-Dist: langchain-community>=0.3.24
Requires-Dist: langchain-openai>=0.3.18
Requires-Dist: langgraph>=0.4.7
Requires-Dist: markdown>=3.8
Requires-Dist: pydantic-settings>=2.9.1
Requires-Dist: pymongo>=4.13.0
Requires-Dist: pymupdf>=1.26.0
Requires-Dist: pymupdf4llm>=0.0.24
Requires-Dist: pypdf2>=3.0.1
Requires-Dist: pytest>=8.3.5
Requires-Dist: python-docx>=1.1.2
Requires-Dist: python-multipart>=0.0.20
Requires-Dist: python-telegram-bot>=22.1
Requires-Dist: qdrant-client>=1.14.2
Requires-Dist: requests>=2.32.3
Requires-Dist: sentence-transformers>=4.1.0
Requires-Dist: telegramify-markdown>=0.5.1
Requires-Dist: uvicorn>=0.34.2
